Metadata-Version: 2.1
Name: web3Batch
Version: 0.0.3
Summary: Library to send batch requests using web3.py
Home-page: https://github.com/zovenor/web3Batch
Author: zovenor
Author-email: zovenor@gmail.com
Project-URL: Bug Tracker, https://github.com/zovenor/web3Batch/issues
Classifier: Programming Language :: Python :: 3
Classifier: License :: OSI Approved :: MIT License
Classifier: Operating System :: OS Independent
Requires-Python: >=3.6
License-File: LICENSE.txt
